garmin_workouts/version.py
garmin_workouts_cli-0.0.1.dist-info/LICENSE
garmin_workouts_cli-0.0.1.dist-info/METADATA
garmin_workouts_cli-0.0.1.dist-info/WHEEL
garmin_workouts_cli-0.0.1.dist-info/top_level.txt
garmin_workouts_cli-0.0.1.dist-info/RECORD
