Metadata-Version: 2.1
Name: garmin-workouts-cli
Version: 0.0.1
Summary: Command line application to work with Garmin Connect Workouts
Home-page: https://github.com/astaruch/garmin-workouts-cli
Author: Andrej Staruch
Author-email: staruch.andrej@gmail.com
License: UNKNOWN
Keywords: garmin,connect,workouts,triathlon,run,calendar
Platform: UNKNOWN
Classifier: Development Status :: 3 - Alpha
Classifier: Environment :: Console
Classifier: Intended Audience :: End Users/Desktop
Classifier: License :: OSI Approved :: GNU General Public License v3 (GPLv3)
Classifier: Natural Language :: English
Classifier: Operating System :: OS Independent
Classifier: Programming Language :: Python :: 3
Classifier: Programming Language :: Python :: 3.5
Classifier: Programming Language :: Python :: 3.6
Classifier: Programming Language :: Python :: 3.7
Classifier: Programming Language :: Python :: 3.8
Classifier: Programming Language :: Python :: 3 :: Only
Requires-Python: >=3.5, <4
